mystipy.py
mystipy-0.7.5.dist-info/METADATA
mystipy-0.7.5.dist-info/WHEEL
mystipy-0.7.5.dist-info/entry_points.txt
mystipy-0.7.5.dist-info/licenses/LICENSE
mystipy-0.7.5.dist-info/RECORD
