Metadata-Version: 2.3
Name: mystipy
Version: 0.7.5
Summary: A simple Python data obfuscation utility.
Project-URL: Homepage, https://github.com/ooojustin/mystipy
Project-URL: Documentation, https://github.com/ooojustin/mystipy#readme
Project-URL: Source, https://github.com/ooojustin/mystipy
Project-URL: Tracker, https://github.com/ooojustin/mystipy/issues
Author-email: Justin Garofolo <justin@garofolo.net>
License: MIT
License-File: LICENSE
Classifier: Development Status :: 4 - Beta
Classifier: Environment :: Console
Classifier: Intended Audience :: Developers
Classifier: Intended Audience :: End Users/Desktop
Classifier: License :: OSI Approved :: MIT License
Classifier: Natural Language :: English
Classifier: Operating System :: OS Independent
Classifier: Programming Language :: Python :: 3.8
Classifier: Programming Language :: Python :: 3.9
Classifier: Programming Language :: Python :: 3.10
Classifier: Programming Language :: Python :: 3.11
Classifier: Programming Language :: Python :: 3.12
Classifier: Topic :: Scientific/Engineering :: Information Analysis
Classifier: Topic :: Security :: Cryptography
Classifier: Topic :: Software Development :: Libraries :: Python Modules
Classifier: Topic :: Text Processing :: General
Classifier: Topic :: Utilities
Requires-Python: >=3.8
